managed_account_client.py
secret_client.py
beyondtrust_bips_library-2.6.0.dist-info/licenses/LICENSE
secrets_safe_library/__init__.py
secrets_safe_library/access_levels.py
secrets_safe_library/access_policies.py
secrets_safe_library/address_groups.py
secrets_safe_library/aliases.py
secrets_safe_library/api_registrations.py
secrets_safe_library/applications.py
secrets_safe_library/assets.py
secrets_safe_library/attribute_types.py
secrets_safe_library/attributes.py
secrets_safe_library/authentication.py
secrets_safe_library/cert_util.py
secrets_safe_library/config.py
secrets_safe_library/core.py
secrets_safe_library/credentials.py
secrets_safe_library/data_classes.py
secrets_safe_library/databases.py
secrets_safe_library/dss_key_policies.py
secrets_safe_library/entitlements.py
secrets_safe_library/entity_types.py
secrets_safe_library/epm_policies.py
secrets_safe_library/exceptions.py
secrets_safe_library/folders.py
secrets_safe_library/functional_accounts.py
secrets_safe_library/isa_requests.py
secrets_safe_library/keystrokes.py
secrets_safe_library/managed_account.py
secrets_safe_library/managed_systems.py
secrets_safe_library/mixins.py
secrets_safe_library/operating_systems.py
secrets_safe_library/oracle_internet_directories.py
secrets_safe_library/organizations.py
secrets_safe_library/password_rules.py
secrets_safe_library/permissions.py
secrets_safe_library/platforms.py
secrets_safe_library/propagation_action_types.py
secrets_safe_library/propagation_actions.py
secrets_safe_library/quick_rules.py
secrets_safe_library/replay.py
secrets_safe_library/request_sets.py
secrets_safe_library/request_termination.py
secrets_safe_library/requests.py
secrets_safe_library/roles.py
secrets_safe_library/safes.py
secrets_safe_library/secrets.py
secrets_safe_library/secrets_safe.py
secrets_safe_library/security.py
secrets_safe_library/session_locking.py
secrets_safe_library/session_termination.py
secrets_safe_library/sessions.py
secrets_safe_library/smart_rules.py
secrets_safe_library/subscription_delivery.py
beyondtrust_bips_library-2.6.0.dist-info/METADATA
beyondtrust_bips_library-2.6.0.dist-info/WHEEL
beyondtrust_bips_library-2.6.0.dist-info/top_level.txt
beyondtrust_bips_library-2.6.0.dist-info/RECORD
