Metadata-Version: 2.4
Name: beyondtrust-bips-library
Version: 2.6.0
Summary: Password Safe API integration written in Python, Abstract complexity of managing secrets with the API.
Author: BeyondTrust Corporation
Author-email: support@beyondtrust.com
License: MIT License
Project-URL: support, https://www.beyondtrust.com/docs/index.htm#support
Keywords: beyondtrust,devops,secrets,secretssafe,security
Classifier: Programming Language :: Python :: 3
Classifier: License :: OSI Approved :: MIT License
Requires-Python: >=3.11
License-File: LICENSE
Requires-Dist: requests==2.32.4
Requires-Dist: urllib3==2.6.3
Requires-Dist: cryptography==44.0.1
Requires-Dist: Cerberus==1.3.5
Requires-Dist: github_action_utils==1.1.0
Dynamic: license-file
